morphoeval/__init__.py
morphoeval/__main__.py
morphoeval/boundary.py
morphoeval/common.py
morphoeval/cooccurrence.py
morphoeval-0.3.0.dist-info/LICENSE
morphoeval-0.3.0.dist-info/METADATA
morphoeval-0.3.0.dist-info/WHEEL
morphoeval-0.3.0.dist-info/entry_points.txt
morphoeval-0.3.0.dist-info/top_level.txt
morphoeval-0.3.0.dist-info/RECORD
