Metadata-Version: 2.1
Name: morphoeval
Version: 0.3.0
Summary: Evaluation for morphological analysis and segmentation
Home-page: https://github.com/svirpioj/morphoeval
Author: Sami Virpioja
Author-email: sami.virpioja@helsinki.fi
Project-URL: Bug Tracker, https://github.com/svirpioj/morphoeval/issues
Classifier: Programming Language :: Python :: 3
Classifier: License :: OSI Approved :: MIT License
Classifier: Operating System :: OS Independent
Requires-Python: >=3.6
License-File: LICENSE
Requires-Dist: numpy
Requires-Dist: pytest
Requires-Dist: ruamel.yaml
Requires-Dist: scipy
Requires-Dist: tqdm
Requires-Dist: munkres
